{
	"info": {
		"_postman_id": "63010fc0-d707-47f4-83ef-b70101f00c66",
		"name": "Funnelsmap my",
		"schema": "https://schema.getpostman.com/json/collection/v2.1.0/collection.json"
	},
	"item": [
		{
			"name": "userRoutes(reg,auth)",
			"item": [
				{
					"name": "signUp",
					"request": {
						"method": "POST",
						"header": [
							{
								"key": "Content-Type",
								"name": "Content-Type",
								"value": "application/json",
								"type": "text"
							}
						],
						"body": {
							"mode": "raw",
							"raw": "{\n\t\"password\":\"artshirin2009@gmail.com\",\n\t\"email\":\"artshirin2009@gmail.com\",\n\t\"firstName\":\"artFirstName\",\n\t\"accountName\":\"artAcc3\"\n}"
						},
						"url": {
							"raw": "http://localhost:9001/sign-up",
							"protocol": "http",
							"host": [
								"localhost"
							],
							"port": "9001",
							"path": [
								"sign-up"
							]
						}
					},
					"response": []
				},
				{
					"name": "signIn",
					"request": {
						"method": "POST",
						"header": [
							{
								"key": "Content-Type",
								"name": "Content-Type",
								"value": "application/json",
								"type": "text"
							}
						],
						"body": {
							"mode": "raw",
							"raw": "{\n\t\"email\":\"artshirin2009@gmail.com\",\n  \"password\": \"artshirin2009@gmail.com\",\n\t\"browser\": \"Mozilla/5.0 (Windows NT 6.3; rv:36.0) Gecko/20100101 Firefox/36.0\",\n\t\"os\":\"dasd\"\n}"
						},
						"url": {
							"raw": "http://localhost:9001/sign-in",
							"protocol": "http",
							"host": [
								"localhost"
							],
							"port": "9001",
							"path": [
								"sign-in"
							]
						}
					},
					"response": []
				},
				{
					"name": "emailValidation",
					"request": {
						"method": "POST",
						"header": [
							{
								"key": "Content-Type",
								"name": "Content-Type",
								"value": "application/json",
								"type": "text"
							}
						],
						"body": {
							"mode": "raw",
							"raw": "{\n\"email\":\"artshirin2009@gmail.com\"\n}"
						},
						"url": {
							"raw": "http://localhost:9001/email-validation",
							"protocol": "http",
							"host": [
								"localhost"
							],
							"port": "9001",
							"path": [
								"email-validation"
							]
						}
					},
					"response": []
				},
				{
					"name": "resetPassword",
					"request": {
						"method": "POST",
						"header": [
							{
								"key": "Content-Type",
								"name": "Content-Type",
								"value": "application/json",
								"type": "text"
							}
						],
						"body": {
							"mode": "raw",
							"raw": "{\n\t\"email\":\"artshirin2009@gmail.com\"\n}"
						},
						"url": {
							"raw": "http://localhost:9001/reset-password",
							"protocol": "http",
							"host": [
								"localhost"
							],
							"port": "9001",
							"path": [
								"reset-password"
							]
						}
					},
					"response": []
				},
				{
					"name": "changePassword",
					"request": {
						"method": "POST",
						"header": [
							{
								"key": "letter-confirm",
								"type": "text",
								"value": "eyJhbGciOiJIUzI1NiIsInR5cCI6IkpXVCJ9.eyJlbWFpbCI6ImFydHNoaXJpbjIwMDlAZ21haWwuY29tIiwiaWF0IjoxNTcyNjEzMDUzLCJleHAiOjE1NzI2MTY2NTN9.ZwgfxD5noAHyfbD1mq1VXO5spnprCSi5BlH_2zUFuf4"
							},
							{
								"key": "",
								"type": "text",
								"value": "",
								"disabled": true
							},
							{
								"key": "Content-Type",
								"name": "Content-Type",
								"type": "text",
								"value": "application/json"
							}
						],
						"body": {
							"mode": "raw",
							"raw": "{\n  \"email\":\"artshirin200449@gmail.com\",\n  \"password\": \"artshirin2009@gmail.com\"\n}"
						},
						"url": {
							"raw": "http://localhost:9001/change-password",
							"protocol": "http",
							"host": [
								"localhost"
							],
							"port": "9001",
							"path": [
								"change-password"
							]
						}
					},
					"response": []
				}
			],
			"protocolProfileBehavior": {}
		},
		{
			"name": "devRoutes",
			"item": [
				{
					"name": "test",
					"request": {
						"method": "POST",
						"header": [
							{
								"key": "Content-Type",
								"name": "Content-Type",
								"value": "application/json",
								"type": "text"
							}
						],
						"body": {
							"mode": "raw",
							"raw": "{\n\t\"password\":\"test2411\",\n\t\"email\":\"vasya@gmail.com\",\n\t\"firstName\":\"testname\",\n\t\"accountName\":\"testName\"\n}"
						},
						"url": {
							"raw": "http://localhost:4000/signUp",
							"protocol": "http",
							"host": [
								"localhost"
							],
							"port": "4000",
							"path": [
								"signUp"
							]
						}
					},
					"response": []
				},
				{
					"name": "serverTest",
					"request": {
						"method": "POST",
						"header": [
							{
								"key": "Content-Type",
								"name": "Content-Type",
								"type": "text",
								"value": "application/json"
							}
						],
						"body": {
							"mode": "raw",
							"raw": "{\n\t\"password\":\"test2411\",\n\t\"email\":\"test@ukr.net\",\n\t\"firstName\":\"testName\",\n\t\"accountName\":\"testAccountName\"\n\t\n}"
						},
						"url": {
							"raw": "http://funnelsmapbackend.qbex.io/signUp",
							"protocol": "http",
							"host": [
								"funnelsmapbackend",
								"qbex",
								"io"
							],
							"path": [
								"signUp"
							]
						}
					},
					"response": []
				},
				{
					"name": "getKeys",
					"request": {
						"method": "GET",
						"header": [],
						"url": {
							"raw": "http://localhost:9001/keys",
							"protocol": "http",
							"host": [
								"localhost"
							],
							"port": "9001",
							"path": [
								"keys"
							]
						}
					},
					"response": []
				}
			],
			"protocolProfileBehavior": {}
		},
		{
			"name": "profileRoutes",
			"item": [
				{
					"name": "update avatar",
					"request": {
						"method": "PATCH",
						"header": [
							{
								"key": "authorization",
								"name": "Content-Type",
								"value": "Bearer eyJhbGciOiJIUzI1NiIsInR5cCI6IkpXVCJ9.eyJwcm9maWxlIjp7InBhc3N3b3JkIjoiJDJiJDEwJFdjamJ2NnNzazk0Ukx2LmdpcDZDUHUvZW5uRFFvSHV1TzY2QmVmbXo1THVCQ0V5UHF0UGxTIiwiZW1haWwiOiJhcnRzaGlyaW4yMDA5QGdtYWlsLmNvbSIsImZpcnN0TmFtZSI6ImFydEZpcnN0TmFtZSIsImFjY291bnROYW1lIjoiYXJ0QWNjMSIsImRlc2NyaXB0aW9uIjpudWxsLCJwaG90b1VybCI6ImxvY2FsaG9zdDozMDAxL2ltYWdlcy9hcnRBY2MxLzE1NzMxMzg4MTgzNzIuanBnIiwibGltaXRlZCI6ZmFsc2UsIl9pZCI6IjVkYzQxZmE1YTY1OTc5MzNhMDhkOGJiOSIsIm15Q29sbGFib3JhdGlvbnMiOltdLCJteVBhcnRuZXJzIjpbXX0sInVzZXJJZCI6IjVkYzQxZmE1YTY1OTc5MzNhMDhkOGJiNyIsImlhdCI6MTU3MzE2NDM5NCwiZXhwIjoxNTczNDIzNTk0fQ.p06Ui87Ysya3aFV-39t4_Y9k9Fd9Zz9PoaGz9-cr_WI",
								"type": "text"
							},
							{
								"key": "Content-Type",
								"value": "Bearer eyJhbGciOiJIUzI1NiIsInR5cCI6IkpXVCJ9.eyJwcm9maWxlIjp7InBhc3N3b3JkIjoiJDJiJDEwJFdjamJ2NnNzazk0Ukx2LmdpcDZDUHUvZW5uRFFvSHV1TzY2QmVmbXo1THVCQ0V5UHF0UGxTIiwiZW1haWwiOiJhcnRzaGlyaW4yMDA5QGdtYWlsLmNvbSIsImZpcnN0TmFtZSI6ImFydEZpcnN0TmFtZSIsImFjY291bnROYW1lIjoiYXJ0QWNjMSIsImRlc2NyaXB0aW9uIjpudWxsLCJwaG90b1VybCI6ImxvY2FsaG9zdDozMDAxL2ltYWdlcy9hcnRBY2MxLzE1NzMxMzg4MTgzNzIuanBnIiwibGltaXRlZCI6ZmFsc2UsIl9pZCI6IjVkYzQxZmE1YTY1OTc5MzNhMDhkOGJiOSIsIm15Q29sbGFib3JhdGlvbnMiOltdLCJteVBhcnRuZXJzIjpbXX0sInVzZXJJZCI6IjVkYzQxZmE1YTY1OTc5MzNhMDhkOGJiNyIsImlhdCI6MTU3MzE2NDM5NCwiZXhwIjoxNTczNDIzNTk0fQ.p06Ui87Ysya3aFV-39t4_Y9k9Fd9Zz9PoaGz9-cr_WI"
							}
						],
						"body": {
							"mode": "formdata",
							"formdata": [
								{
									"key": "avatar",
									"type": "file",
									"src": "/C:/Users/agent/Desktop/adminhot-product_250x250.jpg"
								}
							]
						},
						"url": {
							"raw": "http://localhost:9001/profile/avatar",
							"protocol": "http",
							"host": [
								"localhost"
							],
							"port": "9001",
							"path": [
								"profile",
								"avatar"
							]
						}
					},
					"response": []
				},
				{
					"name": "get photo",
					"request": {
						"method": "GET",
						"header": [],
						"url": {
							"raw": ""
						}
					},
					"response": []
				},
				{
					"name": "updateDescribes",
					"request": {
						"method": "PATCH",
						"header": [
							{
								"key": "authorization",
								"value": "Bearer eyJhbGciOiJIUzI1NiIsInR5cCI6IkpXVCJ9.eyJwcm9maWxlIjp7ImRlc2NyaXB0aW9uIjpudWxsLCJfaWQiOiI1Y2RhZDkwOWQ3MGRmMjAwZGQ4MmRlZDYiLCJwYXNzd29yZCI6IiQyYiQxMCQwdzRhYlU5NTJtYzZPTmI1N0lNRlZPelcuU1JTaktHSUk0MUpuL0lZekNndno4LkVnaFVVbSIsImVtYWlsIjoiMTExMTExMTExMTExMTExMTExMTExMTAwMDAwMDAwMDAwMDAwMDBAdWtyLm5ldCIsImZpcnN0TmFtZSI6ImRkZGRkZGRkZGRkZGQiLCJhY2NvdW50TmFtZSI6ImFhYWFhYWFhYWFhYWFhYWFhIn0sImlhdCI6MTU1Nzg0NjI4MSwiZXhwIjoxNTU4MTA1NDgxfQ.6Z-IcxqwLBoTQ1klSG21U_GU8LO-Wrq7LStu8Yi4DDE",
								"type": "text"
							},
							{
								"key": "Content-Type",
								"name": "Content-Type",
								"value": "application/json",
								"type": "text",
								"disabled": true
							}
						],
						"body": {
							"mode": "raw",
							"raw": "{\n\t\"companyName\":\"122222222222222222222222222222\"\n}"
						},
						"url": {
							"raw": "http://localhost:9001/profile",
							"protocol": "http",
							"host": [
								"localhost"
							],
							"port": "9001",
							"path": [
								"profile"
							]
						}
					},
					"response": []
				},
				{
					"name": "test requestify",
					"request": {
						"method": "POST",
						"header": [],
						"url": {
							"raw": "http://localhost:3001/req-test",
							"protocol": "http",
							"host": [
								"localhost"
							],
							"port": "3001",
							"path": [
								"req-test"
							]
						}
					},
					"response": []
				}
			],
			"protocolProfileBehavior": {}
		},
		{
			"name": "projectRoutes",
			"item": [
				{
					"name": "createProject",
					"request": {
						"method": "POST",
						"header": [
							{
								"key": "Content-Type",
								"name": "Content-Type",
								"value": "application/json",
								"type": "text"
							},
							{
								"key": "authorization",
								"value": "Bearer eyJhbGciOiJIUzI1NiIsInR5cCI6IkpXVCJ9.eyJwcm9maWxlIjp7InBhc3N3b3JkIjoiJDJiJDEwJFdjamJ2NnNzazk0Ukx2LmdpcDZDUHUvZW5uRFFvSHV1TzY2QmVmbXo1THVCQ0V5UHF0UGxTIiwiZW1haWwiOiJhcnRzaGlyaW4yMDA5QGdtYWlsLmNvbSIsImZpcnN0TmFtZSI6ImFydEZpcnN0TmFtZSIsImFjY291bnROYW1lIjoiYXJ0QWNjMSIsImRlc2NyaXB0aW9uIjpudWxsLCJwaG90b1VybCI6ImxvY2FsaG9zdDozMDAxL2ltYWdlcy9hcnRBY2MxLzE1NzMxOTc1MzY5MDcuanBnIiwibGltaXRlZCI6ZmFsc2UsIl9pZCI6IjVkYzQxZmE1YTY1OTc5MzNhMDhkOGJiOSIsIm15Q29sbGFib3JhdGlvbnMiOltdLCJteVBhcnRuZXJzIjpbXX0sInVzZXJJZCI6IjVkYzQxZmE1YTY1OTc5MzNhMDhkOGJiNyIsImlhdCI6MTU3MzE5ODEzNiwiZXhwIjoxNTczNDU3MzM2fQ.9umOW2F8rzu_YztCDL_9ax3vsmDFr4hwlFmuxNdPwWI",
								"type": "text"
							}
						],
						"body": {
							"mode": "raw",
							"raw": "{\n  \"projectName\":\"artTestProject\"\n}"
						},
						"url": {
							"raw": "http://localhost:9001/project",
							"protocol": "http",
							"host": [
								"localhost"
							],
							"port": "9001",
							"path": [
								"project"
							]
						}
					},
					"response": []
				},
				{
					"name": "getAllUsersProjects",
					"request": {
						"method": "GET",
						"header": [
							{
								"key": "authorization",
								"value": "Bearer eyJhbGciOiJIUzI1NiIsInR5cCI6IkpXVCJ9.eyJwcm9maWxlIjp7ImRlc2NyaXB0aW9uIjp7ImNvbXBhbnlOYW1lIjoiMTIyMjIyMjIyMjIyMjIyMjIyMjIyMjIyMjIyMjIyIn0sIl9pZCI6IjVjZGQwODA1NTgwYmEyMDBlZDRiMThhMiIsInBhc3N3b3JkIjoiJDJiJDEwJFhkOEhPajF3czJseUxjNmp3Sk9qRGVOeTZCeW5zMDMzbVBVdW9MTXdTQ1JRM1U4ME1iUkRpIiwiZW1haWwiOiJ0dGQ4NkB1a3IubmV0IiwiZmlyc3ROYW1lIjoidGVzdE5hbWUiLCJhY2NvdW50TmFtZSI6InRlc3RBY2NvdW50TmFtZSJ9LCJpYXQiOjE1NTc5OTI3MjQsImV4cCI6MTU1ODI1MTkyNH0.MwbFjyqUmWbtOvsR68_eMp4bfwATpZmIXvKGxSSR8AM",
								"type": "text"
							}
						],
						"url": {
							"raw": "http://localhost:9001/project",
							"protocol": "http",
							"host": [
								"localhost"
							],
							"port": "9001",
							"path": [
								"project"
							]
						}
					},
					"response": []
				},
				{
					"name": "addColaborator",
					"request": {
						"method": "PATCH",
						"header": [
							{
								"key": "authorization",
								"value": "Bearer eyJhbGciOiJIUzI1NiIsInR5cCI6IkpXVCJ9.eyJwcm9maWxlIjp7ImRlc2NyaXB0aW9uIjp7ImNvbXBhbnlOYW1lIjoiMTIyMjIyMjIyMjIyMjIyMjIyMjIyMjIyMjIyMjIyIn0sIl9pZCI6IjVjZGQwODA1NTgwYmEyMDBlZDRiMThhMiIsInBhc3N3b3JkIjoiJDJiJDEwJFhkOEhPajF3czJseUxjNmp3Sk9qRGVOeTZCeW5zMDMzbVBVdW9MTXdTQ1JRM1U4ME1iUkRpIiwiZW1haWwiOiJ0dGQ4NkB1a3IubmV0IiwiZmlyc3ROYW1lIjoidGVzdE5hbWUiLCJhY2NvdW50TmFtZSI6InRlc3RBY2NvdW50TmFtZSJ9LCJpYXQiOjE1NTc5OTI3MjQsImV4cCI6MTU1ODI1MTkyNH0.MwbFjyqUmWbtOvsR68_eMp4bfwATpZmIXvKGxSSR8AM",
								"type": "text"
							},
							{
								"key": "Content-Type",
								"name": "Content-Type",
								"value": "application/json",
								"type": "text"
							}
						],
						"body": {
							"mode": "raw",
							"raw": "{\n\t\"firstName\":\"ATB\",\n\t\"permissions\":\"view\"\n}"
						},
						"url": {
							"raw": "http://localhost:9001/project_col_add/5cdd541b02aca60079759717?",
							"protocol": "http",
							"host": [
								"localhost"
							],
							"port": "9001",
							"path": [
								"project_col_add",
								"5cdd541b02aca60079759717"
							],
							"query": [
								{
									"key": "authorization",
									"value": "",
									"disabled": true
								}
							]
						}
					},
					"response": []
				},
				{
					"name": "deleteCollaborator",
					"request": {
						"method": "PATCH",
						"header": [
							{
								"key": "authorization",
								"value": "Bearer eyJhbGciOiJIUzI1NiIsInR5cCI6IkpXVCJ9.eyJwcm9maWxlIjp7ImRlc2NyaXB0aW9uIjp7ImNvbXBhbnlOYW1lIjoiMTIyMjIyMjIyMjIyMjIyMjIyMjIyMjIyMjIyMjIyIn0sIl9pZCI6IjVjZGViNTM4NmI4Yjk1MDE4NzE5ODEzYSIsInBhc3N3b3JkIjoiJDJiJDEwJER3YTZudkR6bGF1eWJEdWduU1BXY3VyaWxoeGRrdUZKSGlsT25YNFh0QmY4VHhzbEZ2UFV5IiwiZW1haWwiOiJ0dGQ4NkB1a3IubmV0IiwiZmlyc3ROYW1lIjoidGVzdE5hbWUiLCJhY2NvdW50TmFtZSI6InRlc3RBY2MifSwiaWF0IjoxNTU4MzU3MjIxLCJleHAiOjE1NTg2MTY0MjF9.3fe2_JU3I2W_jFtytva_CvT2pFoAR1IDAqAEPzIgPts",
								"type": "text"
							}
						],
						"body": {
							"mode": "raw",
							"raw": ""
						},
						"url": {
							"raw": "http://localhost:9001/project_col_del/5cdebfaacb275003293e162d/5cdec2140ea54e036b7a9106",
							"protocol": "http",
							"host": [
								"localhost"
							],
							"port": "9001",
							"path": [
								"project_col_del",
								"5cdebfaacb275003293e162d",
								"5cdec2140ea54e036b7a9106"
							]
						}
					},
					"response": []
				},
				{
					"name": "deleteProjectById",
					"request": {
						"method": "DELETE",
						"header": [
							{
								"key": "authorization",
								"value": "Bearer eyJhbGciOiJIUzI1NiIsInR5cCI6IkpXVCJ9.eyJwcm9maWxlIjp7ImRlc2NyaXB0aW9uIjp7ImNvbXBhbnlOYW1lIjoiMTIyMjIyMjIyMjIyMjIyMjIyMjIyMjIyMjIyMjIyIn0sIl9pZCI6IjVjZGQwODA1NTgwYmEyMDBlZDRiMThhMiIsInBhc3N3b3JkIjoiJDJiJDEwJFhkOEhPajF3czJseUxjNmp3Sk9qRGVOeTZCeW5zMDMzbVBVdW9MTXdTQ1JRM1U4ME1iUkRpIiwiZW1haWwiOiJ0dGQ4NkB1a3IubmV0IiwiZmlyc3ROYW1lIjoidGVzdE5hbWUiLCJhY2NvdW50TmFtZSI6InRlc3RBY2NvdW50TmFtZSJ9LCJpYXQiOjE1NTc5OTI3MjQsImV4cCI6MTU1ODI1MTkyNH0.MwbFjyqUmWbtOvsR68_eMp4bfwATpZmIXvKGxSSR8AM",
								"type": "text"
							}
						],
						"body": {
							"mode": "raw",
							"raw": ""
						},
						"url": {
							"raw": "http://localhost:9001/project/",
							"protocol": "http",
							"host": [
								"localhost"
							],
							"port": "9001",
							"path": [
								"project",
								""
							]
						}
					},
					"response": []
				},
				{
					"name": "getAllProjectsFromDB",
					"request": {
						"method": "GET",
						"header": [
							{
								"key": "authorization",
								"value": "Bearer eyJhbGciOiJIUzI1NiIsInR5cCI6IkpXVCJ9.eyJwcm9maWxlIjp7ImRlc2NyaXB0aW9uIjp7ImNvbXBhbnlOYW1lIjoiMTIyMjIyMjIyMjIyMjIyMjIyMjIyMjIyMjIyMjIyIn0sIl9pZCI6IjVjZGQwODA1NTgwYmEyMDBlZDRiMThhMiIsInBhc3N3b3JkIjoiJDJiJDEwJFhkOEhPajF3czJseUxjNmp3Sk9qRGVOeTZCeW5zMDMzbVBVdW9MTXdTQ1JRM1U4ME1iUkRpIiwiZW1haWwiOiJ0dGQ4NkB1a3IubmV0IiwiZmlyc3ROYW1lIjoidGVzdE5hbWUiLCJhY2NvdW50TmFtZSI6InRlc3RBY2NvdW50TmFtZSJ9LCJpYXQiOjE1NTc5OTI3MjQsImV4cCI6MTU1ODI1MTkyNH0.MwbFjyqUmWbtOvsR68_eMp4bfwATpZmIXvKGxSSR8AM",
								"type": "text"
							}
						],
						"url": {
							"raw": "http://localhost:9001/projects",
							"protocol": "http",
							"host": [
								"localhost"
							],
							"port": "9001",
							"path": [
								"projects"
							]
						}
					},
					"response": []
				}
			],
			"protocolProfileBehavior": {}
		},
		{
			"name": "funnelRoutes",
			"item": [
				{
					"name": "createFunnel",
					"request": {
						"method": "POST",
						"header": [
							{
								"key": "authorization",
								"value": "Bearer eyJhbGciOiJIUzI1NiIsInR5cCI6IkpXVCJ9.eyJwcm9maWxlIjp7InBhc3N3b3JkIjoiJDJiJDEwJFdjamJ2NnNzazk0Ukx2LmdpcDZDUHUvZW5uRFFvSHV1TzY2QmVmbXo1THVCQ0V5UHF0UGxTIiwiZW1haWwiOiJhcnRzaGlyaW4yMDA5QGdtYWlsLmNvbSIsImZpcnN0TmFtZSI6ImFydEZpcnN0TmFtZSIsImFjY291bnROYW1lIjoiYXJ0QWNjMSIsImRlc2NyaXB0aW9uIjpudWxsLCJwaG90b1VybCI6ImxvY2FsaG9zdDozMDAxL2ltYWdlcy9hcnRBY2MxLzE1NzMxOTc1MzY5MDcuanBnIiwibGltaXRlZCI6ZmFsc2UsIl9pZCI6IjVkYzQxZmE1YTY1OTc5MzNhMDhkOGJiOSIsIm15Q29sbGFib3JhdGlvbnMiOltdLCJteVBhcnRuZXJzIjpbXX0sInVzZXJJZCI6IjVkYzQxZmE1YTY1OTc5MzNhMDhkOGJiNyIsImlhdCI6MTU3MzE5ODEzNiwiZXhwIjoxNTczNDU3MzM2fQ.9umOW2F8rzu_YztCDL_9ax3vsmDFr4hwlFmuxNdPwWI",
								"type": "text"
							},
							{
								"key": "Content-Type",
								"name": "Content-Type",
								"value": "application/json",
								"type": "text"
							}
						],
						"body": {
							"mode": "raw",
							"raw": "{\n\t\"funnelName\":\"TESTYOURSELF333\",\n\t\"funnelBody\":\"testFunnelBody\"\n}"
						},
						"url": {
							"raw": "http://localhost:9001/funnel/5dc51a86ff896c30f06361a2",
							"protocol": "http",
							"host": [
								"localhost"
							],
							"port": "9001",
							"path": [
								"funnel",
								"5dc51a86ff896c30f06361a2"
							]
						}
					},
					"response": []
				},
				{
					"name": "getFunellSVG",
					"request": {
						"method": "GET",
						"header": [
							{
								"key": "authorization",
								"type": "text",
								"value": "Bearer eyJhbGciOiJIUzI1NiIsInR5cCI6IkpXVCJ9.eyJwcm9maWxlIjp7InBhc3N3b3JkIjoiJDJiJDEwJFdjamJ2NnNzazk0Ukx2LmdpcDZDUHUvZW5uRFFvSHV1TzY2QmVmbXo1THVCQ0V5UHF0UGxTIiwiZW1haWwiOiJhcnRzaGlyaW4yMDA5QGdtYWlsLmNvbSIsImZpcnN0TmFtZSI6ImFydEZpcnN0TmFtZSIsImFjY291bnROYW1lIjoiYXJ0QWNjMSIsImRlc2NyaXB0aW9uIjpudWxsLCJwaG90b1VybCI6ImxvY2FsaG9zdDozMDAxL2ltYWdlcy9hcnRBY2MxLzE1NzMxOTc1MzY5MDcuanBnIiwibGltaXRlZCI6ZmFsc2UsIl9pZCI6IjVkYzQxZmE1YTY1OTc5MzNhMDhkOGJiOSIsIm15Q29sbGFib3JhdGlvbnMiOltdLCJteVBhcnRuZXJzIjpbXX0sInVzZXJJZCI6IjVkYzQxZmE1YTY1OTc5MzNhMDhkOGJiNyIsImlhdCI6MTU3MzE5ODEzNiwiZXhwIjoxNTczNDU3MzM2fQ.9umOW2F8rzu_YztCDL_9ax3vsmDFr4hwlFmuxNdPwWI"
							}
						],
						"url": {
							"raw": "http://localhost:9001/funnel/svg",
							"protocol": "http",
							"host": [
								"localhost"
							],
							"port": "9001",
							"path": [
								"funnel",
								"svg"
							]
						}
					},
					"response": []
				},
				{
					"name": "addFunnelDiagramAndBackground",
					"request": {
						"method": "PATCH",
						"header": [
							{
								"key": "authorization",
								"type": "text",
								"value": "Bearer eyJhbGciOiJIUzI1NiIsInR5cCI6IkpXVCJ9.eyJwcm9maWxlIjp7InBhc3N3b3JkIjoiJDJiJDEwJFdjamJ2NnNzazk0Ukx2LmdpcDZDUHUvZW5uRFFvSHV1TzY2QmVmbXo1THVCQ0V5UHF0UGxTIiwiZW1haWwiOiJhcnRzaGlyaW4yMDA5QGdtYWlsLmNvbSIsImZpcnN0TmFtZSI6ImFydEZpcnN0TmFtZSIsImFjY291bnROYW1lIjoiYXJ0QWNjMSIsImRlc2NyaXB0aW9uIjpudWxsLCJwaG90b1VybCI6ImxvY2FsaG9zdDozMDAxL2ltYWdlcy9hcnRBY2MxLzE1NzMxOTc1MzY5MDcuanBnIiwibGltaXRlZCI6ZmFsc2UsIl9pZCI6IjVkYzQxZmE1YTY1OTc5MzNhMDhkOGJiOSIsIm15Q29sbGFib3JhdGlvbnMiOltdLCJteVBhcnRuZXJzIjpbXX0sInVzZXJJZCI6IjVkYzQxZmE1YTY1OTc5MzNhMDhkOGJiNyIsImlhdCI6MTU3MzE5ODEzNiwiZXhwIjoxNTczNDU3MzM2fQ.9umOW2F8rzu_YztCDL_9ax3vsmDFr4hwlFmuxNdPwWI"
							},
							{
								"key": "Content-Type",
								"name": "Content-Type",
								"type": "text",
								"value": "application/json"
							}
						],
						"body": {
							"mode": "formdata",
							"formdata": [
								{
									"key": "funnelBackground",
									"type": "file",
									"src": "/C:/Users/agent/Desktop/fun_back.jpg"
								}
							]
						},
						"url": {
							"raw": "http://localhost:9001/funnel/diagram/5dc51b55ff896c30f06361a4",
							"protocol": "http",
							"host": [
								"localhost"
							],
							"port": "9001",
							"path": [
								"funnel",
								"diagram",
								"5dc51b55ff896c30f06361a4"
							]
						}
					},
					"response": []
				},
				{
					"name": "getScreenshot",
					"request": {
						"method": "POST",
						"header": [
							{
								"key": "authorization",
								"type": "text",
								"value": "Bearer eyJhbGciOiJIUzI1NiIsInR5cCI6IkpXVCJ9.eyJwcm9maWxlIjp7InBhc3N3b3JkIjoiJDJiJDEwJFdjamJ2NnNzazk0Ukx2LmdpcDZDUHUvZW5uRFFvSHV1TzY2QmVmbXo1THVCQ0V5UHF0UGxTIiwiZW1haWwiOiJhcnRzaGlyaW4yMDA5QGdtYWlsLmNvbSIsImZpcnN0TmFtZSI6ImFydEZpcnN0TmFtZSIsImFjY291bnROYW1lIjoiYXJ0QWNjMSIsImRlc2NyaXB0aW9uIjpudWxsLCJwaG90b1VybCI6ImxvY2FsaG9zdDozMDAxL2ltYWdlcy9hcnRBY2MxLzE1NzMxOTc1MzY5MDcuanBnIiwibGltaXRlZCI6ZmFsc2UsIl9pZCI6IjVkYzQxZmE1YTY1OTc5MzNhMDhkOGJiOSIsIm15Q29sbGFib3JhdGlvbnMiOltdLCJteVBhcnRuZXJzIjpbXX0sInVzZXJJZCI6IjVkYzQxZmE1YTY1OTc5MzNhMDhkOGJiNyIsImlhdCI6MTU3MzE5ODEzNiwiZXhwIjoxNTczNDU3MzM2fQ.9umOW2F8rzu_YztCDL_9ax3vsmDFr4hwlFmuxNdPwWI"
							},
							{
								"key": "Content-Type",
								"name": "Content-Type",
								"type": "text",
								"value": "application/json"
							}
						],
						"body": {
							"mode": "formdata",
							"formdata": [
								{
									"key": "screenshot",
									"type": "file",
									"src": "/C:/Users/agent/Desktop/sceen.jpg"
								},
								{
									"key": "funnelsId",
									"value": "5dc51b55ff896c30f06361a4",
									"type": "text"
								},
								{
									"key": "permissions",
									"value": "1",
									"type": "text"
								}
							]
						},
						"url": {
							"raw": "http://localhost:9001/funnel/diagram/screenshot",
							"protocol": "http",
							"host": [
								"localhost"
							],
							"port": "9001",
							"path": [
								"funnel",
								"diagram",
								"screenshot"
							]
						}
					},
					"response": []
				},
				{
					"name": "getAllProjectFunnels",
					"request": {
						"method": "GET",
						"header": [
							{
								"key": "authorization",
								"value": "Bearer eyJhbGciOiJIUzI1NiIsInR5cCI6IkpXVCJ9.eyJwcm9maWxlIjp7ImRlc2NyaXB0aW9uIjpudWxsLCJfaWQiOiI1Y2RlYjUzODZiOGI5NTAxODcxOTgxM2EiLCJwYXNzd29yZCI6IiQyYiQxMCREd2E2bnZEemxhdXliRHVnblNQV2N1cmlsaHhka3VGSkhpbE9uWDRYdEJmOFR4c2xGdlBVeSIsImVtYWlsIjoidHRkODZAdWtyLm5ldCIsImZpcnN0TmFtZSI6InRlc3ROYW1lIiwiYWNjb3VudE5hbWUiOiJ0ZXN0QWNjIn0sImlhdCI6MTU1ODA5OTI1NiwiZXhwIjoxNTU4MzU4NDU2fQ.WuHjiUlnZ8vW2ucyaaijtdfhM9ZF5nOer1QuKYoPIWo",
								"type": "text"
							}
						],
						"url": {
							"raw": "http://localhost:9001/funnels/5cdeb56c6b8b95018719813c",
							"protocol": "http",
							"host": [
								"localhost"
							],
							"port": "9001",
							"path": [
								"funnels",
								"5cdeb56c6b8b95018719813c"
							]
						}
					},
					"response": []
				},
				{
					"name": "collaborateFunnel",
					"request": {
						"method": "POST",
						"header": [
							{
								"key": "authorization",
								"value": "Bearer eyJhbGciOiJIUzI1NiIsInR5cCI6IkpXVCJ9.eyJwcm9maWxlIjp7ImRlc2NyaXB0aW9uIjpudWxsLCJfaWQiOiI1Y2RlYjUzODZiOGI5NTAxODcxOTgxM2EiLCJwYXNzd29yZCI6IiQyYiQxMCREd2E2bnZEemxhdXliRHVnblNQV2N1cmlsaHhka3VGSkhpbE9uWDRYdEJmOFR4c2xGdlBVeSIsImVtYWlsIjoidHRkODZAdWtyLm5ldCIsImZpcnN0TmFtZSI6InRlc3ROYW1lIiwiYWNjb3VudE5hbWUiOiJ0ZXN0QWNjIn0sImlhdCI6MTU1ODA5OTI1NiwiZXhwIjoxNTU4MzU4NDU2fQ.WuHjiUlnZ8vW2ucyaaijtdfhM9ZF5nOer1QuKYoPIWo",
								"type": "text"
							}
						],
						"body": {
							"mode": "raw",
							"raw": ""
						},
						"url": {
							"raw": "http://localhost:9001/funnel_col/5cdebfcfcb275003293e162f/5cdec2140ea54e036b7a9106",
							"protocol": "http",
							"host": [
								"localhost"
							],
							"port": "9001",
							"path": [
								"funnel_col",
								"5cdebfcfcb275003293e162f",
								"5cdec2140ea54e036b7a9106"
							]
						}
					},
					"response": []
				},
				{
					"name": "deleteFunnel",
					"request": {
						"method": "DELETE",
						"header": [
							{
								"key": "authorization",
								"value": "Bearer eyJhbGciOiJIUzI1NiIsInR5cCI6IkpXVCJ9.eyJwcm9maWxlIjp7ImRlc2NyaXB0aW9uIjp7ImNvbXBhbnlOYW1lIjoiMTIyMjIyMjIyMjIyMjIyMjIyMjIyMjIyMjIyMjIyIn0sIl9pZCI6IjVjZGViNTM4NmI4Yjk1MDE4NzE5ODEzYSIsInBhc3N3b3JkIjoiJDJiJDEwJER3YTZudkR6bGF1eWJEdWduU1BXY3VyaWxoeGRrdUZKSGlsT25YNFh0QmY4VHhzbEZ2UFV5IiwiZW1haWwiOiJ0dGQ4NkB1a3IubmV0IiwiZmlyc3ROYW1lIjoidGVzdE5hbWUiLCJhY2NvdW50TmFtZSI6InRlc3RBY2MifSwiaWF0IjoxNTU4MzU3MjIxLCJleHAiOjE1NTg2MTY0MjF9.3fe2_JU3I2W_jFtytva_CvT2pFoAR1IDAqAEPzIgPts",
								"type": "text"
							}
						],
						"body": {
							"mode": "raw",
							"raw": ""
						},
						"url": {
							"raw": "http://localhost:9001/funnel/5cdebfaacb275003293e162d/5ce2a9df2b961004c455b8aa",
							"protocol": "http",
							"host": [
								"localhost"
							],
							"port": "9001",
							"path": [
								"funnel",
								"5cdebfaacb275003293e162d",
								"5ce2a9df2b961004c455b8aa"
							]
						}
					},
					"response": []
				},
				{
					"name": "createColUrl",
					"request": {
						"method": "POST",
						"header": [
							{
								"key": "authorization",
								"value": "Bearer eyJhbGciOiJIUzI1NiIsInR5cCI6IkpXVCJ9.eyJwcm9maWxlIjp7ImRlc2NyaXB0aW9uIjp7ImNvbXBhbnlOYW1lIjoiMTIyMjIyMjIyMjIyMjIyMjIyMjIyMjIyMjIyMjIyIn0sIl9pZCI6IjVjZGViNTM4NmI4Yjk1MDE4NzE5ODEzYSIsInBhc3N3b3JkIjoiJDJiJDEwJER3YTZudkR6bGF1eWJEdWduU1BXY3VyaWxoeGRrdUZKSGlsT25YNFh0QmY4VHhzbEZ2UFV5IiwiZW1haWwiOiJ0dGQ4NkB1a3IubmV0IiwiZmlyc3ROYW1lIjoidGVzdE5hbWUiLCJhY2NvdW50TmFtZSI6InRlc3RBY2MifSwiaWF0IjoxNTU4NTEwNDE3LCJleHAiOjE1NTg3Njk2MTd9.ICfDKS14vtUN3FoZxKuC_Vfx7rh-vdJ8UMq2nqJ4eGs",
								"type": "text"
							},
							{
								"key": "Content-Type",
								"name": "Content-Type",
								"value": "application/json",
								"type": "text"
							}
						],
						"body": {
							"mode": "raw",
							"raw": "{\n   \"funnelsId\":[\"5ce51cfb4b8d610288601205\"],\n   \"permissions\":\"Edit\"\n}"
						},
						"url": {
							"raw": "http://localhost:9001/funnel_col_url",
							"protocol": "http",
							"host": [
								"localhost"
							],
							"port": "9001",
							"path": [
								"funnel_col_url"
							]
						}
					},
					"response": []
				},
				{
					"name": "createCollaborator",
					"request": {
						"method": "POST",
						"header": [
							{
								"key": "collaborate-confirm",
								"value": "eyJhbGciOiJIUzI1NiIsInR5cCI6IkpXVCJ9.eyJmdW5uZWxzSWQiOlsiNWNlNTFjZmI0YjhkNjEwMjg4NjAxMjA1Il0sInBlcm1pc3Npb25zIjoiRWRpdCIsImlhdCI6MTU1ODUxOTA2NH0.NE7O_S_1-xcV4BgU66WczF68blacTfx9SvEpvbBOCd0",
								"type": "text"
							},
							{
								"key": "Content-Type",
								"name": "Content-Type",
								"value": "application/json",
								"type": "text"
							},
							{
								"key": "authorization",
								"value": "Bearer eyJhbGciOiJIUzI1NiIsInR5cCI6IkpXVCJ9.eyJwcm9maWxlIjp7ImRlc2NyaXB0aW9uIjp7IkZyZWVsYW5jZXIiOiJGcmVlbGFuY2VyIn0sIl9pZCI6IjVjZGVjMjE0MGVhNTRlMDM2YjdhOTEwNiIsInBhc3N3b3JkIjoiJDJiJDEwJGdPOGRLdk02aGYxNXlwU1IuRUxNUXUvOHNyTS5wV2ZqcnBuaEpGbmxXV3hNcTdpczJnN0dlIiwiZW1haWwiOiJ0aGVqdXN0dmljQGdtYWlsLmNvbSIsImZpcnN0TmFtZSI6IlByb2Zlc3NvciIsImFjY291bnROYW1lIjoiUHJvZmVzc29yZW5rbyJ9LCJpYXQiOjE1NTg1MTM3MDIsImV4cCI6MTU1ODc3MjkwMn0.QZKxS4fdMjGJF2_z-nGDhFOiq5pU-gOcQiAKOSPDnu8",
								"type": "text"
							}
						],
						"body": {
							"mode": "raw",
							"raw": "{\n\t\"user_id\": \"\"\n}"
						},
						"url": {
							"raw": "http://localhost:9001/funnel_col_add",
							"protocol": "http",
							"host": [
								"localhost"
							],
							"port": "9001",
							"path": [
								"funnel_col_add"
							]
						}
					},
					"response": []
				},
				{
					"name": "getAllCollaboratedToUserFunnels",
					"request": {
						"method": "GET",
						"header": [
							{
								"key": "authorization",
								"value": "Bearer eyJhbGciOiJIUzI1NiIsInR5cCI6IkpXVCJ9.eyJwcm9maWxlIjp7ImRlc2NyaXB0aW9uIjp7ImNvbXBhbnlOYW1lIjoiMTIyMjIyMjIyMjIyMjIyMjIyMjIyMjIyMjIyMjIyIn0sIl9pZCI6IjVjZGViNTM4NmI4Yjk1MDE4NzE5ODEzYSIsInBhc3N3b3JkIjoiJDJiJDEwJER3YTZudkR6bGF1eWJEdWduU1BXY3VyaWxoeGRrdUZKSGlsT25YNFh0QmY4VHhzbEZ2UFV5IiwiZW1haWwiOiJ0dGQ4NkB1a3IubmV0IiwiZmlyc3ROYW1lIjoidGVzdE5hbWUiLCJhY2NvdW50TmFtZSI6InRlc3RBY2MifSwiaWF0IjoxNTU4NDM4NDQ3LCJleHAiOjE1NTg2OTc2NDd9.RIwyEewjhYjncgG8pBfGEzbUlGq0PMPVLBsjGGgbw5E",
								"type": "text"
							}
						],
						"url": {
							"raw": "http://localhost:9001/funnels_col?",
							"protocol": "http",
							"host": [
								"localhost"
							],
							"port": "9001",
							"path": [
								"funnels_col"
							],
							"query": [
								{
									"key": "",
									"value": null
								}
							]
						}
					},
					"response": []
				},
				{
					"name": "getAllFunnelsCollaborators",
					"protocolProfileBehavior": {
						"disableBodyPruning": true
					},
					"request": {
						"method": "GET",
						"header": [
							{
								"key": "authorization",
								"value": "Bearer eyJhbGciOiJIUzI1NiIsInR5cCI6IkpXVCJ9.eyJwcm9maWxlIjp7ImRlc2NyaXB0aW9uIjp7ImNvbXBhbnlOYW1lIjoiMTIyMjIyMjIyMjIyMjIyMjIyMjIyMjIyMjIyMjIyIn0sIl9pZCI6IjVjZGViNTM4NmI4Yjk1MDE4NzE5ODEzYSIsInBhc3N3b3JkIjoiJDJiJDEwJER3YTZudkR6bGF1eWJEdWduU1BXY3VyaWxoeGRrdUZKSGlsT25YNFh0QmY4VHhzbEZ2UFV5IiwiZW1haWwiOiJ0dGQ4NkB1a3IubmV0IiwiZmlyc3ROYW1lIjoidGVzdE5hbWUiLCJhY2NvdW50TmFtZSI6InRlc3RBY2MifSwiaWF0IjoxNTU4NTEwNDE3LCJleHAiOjE1NTg3Njk2MTd9.ICfDKS14vtUN3FoZxKuC_Vfx7rh-vdJ8UMq2nqJ4eGs",
								"type": "text"
							},
							{
								"key": "Content-Type",
								"name": "Content-Type",
								"value": "application/json",
								"type": "text"
							}
						],
						"body": {
							"mode": "raw",
							"raw": "{\n  \"funnelsId\":[\"5ce4fd1fbd08f4019e9d8bba\",\"5ce51022dfac8f0095740b73\"]\n}"
						},
						"url": {
							"raw": "http://localhost:9001/funnel_col_get/5ce52f9307db4702e01e85f2",
							"protocol": "http",
							"host": [
								"localhost"
							],
							"port": "9001",
							"path": [
								"funnel_col_get",
								"5ce52f9307db4702e01e85f2"
							]
						}
					},
					"response": []
				}
			],
			"protocolProfileBehavior": {}
		}
	],
	"event": [
		{
			"listen": "prerequest",
			"script": {
				"id": "6069039c-b9cb-41e6-ac40-774afa92ef7d",
				"type": "text/javascript",
				"exec": [
					""
				]
			}
		},
		{
			"listen": "test",
			"script": {
				"id": "4c33e314-19bb-4b7c-8293-fcc4d725ab3a",
				"type": "text/javascript",
				"exec": [
					""
				]
			}
		}
	],
	"protocolProfileBehavior": {}
}